bp_monitor/__init__.py
bp_monitor/app.py
bp_monitor/run.py
bp_monitor-0.1.0.dist-info/LICENSE
bp_monitor-0.1.0.dist-info/METADATA
bp_monitor-0.1.0.dist-info/WHEEL
bp_monitor-0.1.0.dist-info/entry_points.txt
bp_monitor-0.1.0.dist-info/top_level.txt
bp_monitor-0.1.0.dist-info/RECORD
