Metadata-Version: 2.1
Name: bp-monitor
Version: 0.1.0
Summary: Allows use to input bloood pressure vaules and creates reports including visualisations indicating BP treds over time
Home-page: https://github.com/bokey007/bp_monitor
Author: Sudhir Arvind Deshmukh
License-File: LICENSE
Requires-Dist: pandas (==1.5.3)
Requires-Dist: plotly (==5.13.1)
Requires-Dist: reportlab (==4.0.9)
Requires-Dist: streamlit (==1.13.0)
